CHANGES.rst
CONTRIBUTORS.rst
DEVELOP.rst
LICENSE.rst
MANIFEST.in
README.rst
setup.cfg
setup.py
docs/conf.py
docs/index.rst
src/collective/__init__.py
src/collective.edtf_behavior.egg-info/PKG-INFO
src/collective.edtf_behavior.egg-info/SOURCES.txt
src/collective.edtf_behavior.egg-info/dependency_links.txt
src/collective.edtf_behavior.egg-info/entry_points.txt
src/collective.edtf_behavior.egg-info/namespace_packages.txt
src/collective.edtf_behavior.egg-info/not-zip-safe
src/collective.edtf_behavior.egg-info/requires.txt
src/collective.edtf_behavior.egg-info/top_level.txt
src/collective/edtf_behavior/__init__.py
src/collective/edtf_behavior/configure.zcml
src/collective/edtf_behavior/interfaces.py
src/collective/edtf_behavior/permissions.zcml
src/collective/edtf_behavior/setuphandlers.py
src/collective/edtf_behavior/testing.py
src/collective/edtf_behavior/upgrades.py
src/collective/edtf_behavior/upgrades.zcml
src/collective/edtf_behavior/behaviors/__init__.py
src/collective/edtf_behavior/behaviors/configure.zcml
src/collective/edtf_behavior/behaviors/edtf_date.py
src/collective/edtf_behavior/indexers/__init__.py
src/collective/edtf_behavior/indexers/configure.zcml
src/collective/edtf_behavior/indexers/edtf.py
src/collective/edtf_behavior/locales/README.rst
src/collective/edtf_behavior/locales/__init__.py
src/collective/edtf_behavior/locales/collective.edtf_behavior.pot
src/collective/edtf_behavior/locales/update.py
src/collective/edtf_behavior/locales/update.sh
src/collective/edtf_behavior/locales/en/LC_MESSAGES/collective.edtf_behavior.po
src/collective/edtf_behavior/profiles/default/browserlayer.xml
src/collective/edtf_behavior/profiles/default/catalog.xml
src/collective/edtf_behavior/profiles/default/metadata.xml
src/collective/edtf_behavior/profiles/default/registry.xml
src/collective/edtf_behavior/profiles/default/rolemap.xml
src/collective/edtf_behavior/profiles/uninstall/browserlayer.xml
src/collective/edtf_behavior/tests/__init__.py
src/collective/edtf_behavior/tests/test_behavior_edtf_date.py
src/collective/edtf_behavior/tests/test_edtf_search_on_indexes.py
src/collective/edtf_behavior/tests/test_robot.py
src/collective/edtf_behavior/tests/test_setup.py
src/collective/edtf_behavior/tests/robot/keywords.robot
src/collective/edtf_behavior/tests/robot/test_example.robot