Metadata-Version: 2.1
Name: collective.edtf-behavior
Version: 1.0.3
Summary: A EDTF behavior for Plone.
Home-page: https://pypi.python.org/pypi/collective.edtf_behavior
Author: Maik Derstappen
Author-email: md@derico.de
License: GPL version 2
Keywords: Python Plone
Platform: UNKNOWN
Classifier: Environment :: Web Environment
Classifier: Framework :: Plone
Classifier: Framework :: Plone :: Addon
Classifier: Framework :: Plone :: 5.1
Classifier: Framework :: Plone :: 5.2
Classifier: Programming Language :: Python
Classifier: Programming Language :: Python :: 2.7
Classifier: Programming Language :: Python :: 3.7
Classifier: Operating System :: OS Independent
Classifier: License :: OSI Approved :: GNU General Public License v2 (GPLv2)
Requires-Python: ==2.7, >=3.7
Provides-Extra: test
